tools/__init__.py
tools/coord_convert/__init__.py
tools/coord_convert/bd2gcj.py
tools/db/__init__.py
tools/db/mysql_helper.py
t_tools-0.0.1.dist-info/METADATA
t_tools-0.0.1.dist-info/WHEEL
t_tools-0.0.1.dist-info/entry_points.txt
t_tools-0.0.1.dist-info/top_level.txt
t_tools-0.0.1.dist-info/RECORD
