Metadata-Version: 2.1
Name: t-tools
Version: 0.0.1
Summary: t-tools
Home-page: https://github.com/coco369/tools
Author: wanghaifei
Author-email: 779598160@qq.com
License: UNKNOWN
Download-URL: https://github.com/coco369/tools
Keywords: command,line,tool
Platform: UNKNOWN
Requires-Dist: python3.7.6
